autoacu/__init__.py
autoacu/a2cu.py
autoacu/a3cu.py
autoacu/model.py
autoacu-0.3.0.dist-info/METADATA
autoacu-0.3.0.dist-info/WHEEL
autoacu-0.3.0.dist-info/top_level.txt
autoacu-0.3.0.dist-info/RECORD
