Metadata-Version: 2.1
Name: autoacu
Version: 0.3.0
Summary: Interpretable and Efficient Automatic Summarization Evaluation Metrics
Home-page: https://github.com/Yale-LILY/AutoACU
Provides-Extra: stable
Requires-Dist: torch (==1.12.1) ; extra == 'stable'
Requires-Dist: transformers (==4.21.2) ; extra == 'stable'
